{"request_id": "request_a95ffae9299c4767a85c125cd4febfb1", "participant_id": "p05021329", "description": "I have something that I want to run, but whenever I run & expect it to prompt the user, I get an error saying that RGX is not connect?", "category": "I thought I knew how to use this, but it didn\u2019t do what I expected\u2026", "created_at": "02/05/2024 13:59:41", "closed_at": "02/05/2024 14:18:28", "feedback": [{"rate_satisfaction": "Neutral", "most_useful_category": "None", "was_category_correct": "Yes"}]}